LICENSE.md
MANIFEST.in
README.rst
setup.cfg
setup.py
space/__init__.py
space/__main__.py
space/ccsds.py
space/clock.py
space/config.py
space/events.py
space/passes.py
space/phase.py
space/planet.py
space/sat.py
space/station.py
space/utils.py
space/wspace.py
space/map/__init__.py
space/map/background.py
space/map/map.py
space/map/wephem.py
space/static/earth.png
space/static/mars.png
space/static/moon.png
space/static/venus.png
space/tle/__init__.py
space/tle/celestrak.py
space/tle/common.py
space/tle/db.py
space/tle/spacetrack.py
space_command.egg-info/PKG-INFO
space_command.egg-info/SOURCES.txt
space_command.egg-info/dependency_links.txt
space_command.egg-info/entry_points.txt
space_command.egg-info/not-zip-safe
space_command.egg-info/requires.txt
space_command.egg-info/top_level.txt
tests/test_ccsds.py
tests/test_clock.py
tests/test_config.py
tests/test_main.py
tests/test_passes.py
tests/test_planets.py
tests/test_sat.py
tests/test_tle.py
tests/test_utils.py