Metadata-Version: 2.1
Name: space-command
Version: 0.7.3
Summary: Space Command
Author: Jules David
Author-email: jules@onada.fr
License: MIT License
Keywords: flight dynamic,satellite,space
Classifier: Development Status :: 2 - Pre-Alpha
Classifier: Intended Audience :: Science/Research
Classifier: License :: OSI Approved :: MIT License
Classifier: Programming Language :: Python :: 3.7
Classifier: Programming Language :: Python :: 3.8
Classifier: Programming Language :: Python :: 3.9
Classifier: Programming Language :: Python :: 3.10
Classifier: Programming Language :: Python :: 3.11
Classifier: Topic :: Scientific/Engineering :: Astronomy
Classifier: Topic :: Scientific/Engineering :: Physics
Provides-Extra: tests
License-File: LICENSE.md
